Metadata-Version: 1.1
Name: httpie-visionect-auth
Version: 0.0.1
Summary: HMAC Auth plugin for Joan Visionect and HTTPie.
Home-page: https://github.com/pcoueffin/httpie-visionect-auth
Author: Pierre Coueffin
Author-email: pcoueffin@gmail.com
License: MIT
Download-URL: https://github.com/pcoueffin/httpie-visionect-auth
Platform: UNKNOWN
Classifier: Development Status :: 3 - Alpha
Classifier: Programming Language :: Python
Classifier: Intended Audience :: Developers
Classifier: Environment :: Plugins
Classifier: License :: OSI Approved :: MIT License
Classifier: Topic :: Internet :: WWW/HTTP
Classifier: Topic :: Utilities
